pkg/__init__.py
pkg/mainentry.py
pkg/sample.py
pkg/subpkg/__init__.py
pkg/subpkg/submoduleone.py
pkg/subpkg/submoduletwo.py
pythonDistribution-1.0.0.dist-info/METADATA
pythonDistribution-1.0.0.dist-info/WHEEL
pythonDistribution-1.0.0.dist-info/top_level.txt
pythonDistribution-1.0.0.dist-info/RECORD
