Metadata-Version: 2.1
Name: pythonDistribution
Version: 1.0.0
Summary: Skeleton for setuptools and project structure
Home-page: UNKNOWN
License: UNKNOWN
Platform: UNKNOWN
